CHANGELOG.txt
LICENSE.txt
MANIFEST.in
README.md
Setup.py
requirements.txt
setup.py
.ipynb_checkpoints/LICENSE-checkpoint.txt
LasBuildSeg/LasBuildSeg.py
LasBuildSeg/__init__.py
LasBuildSeg.egg-info/PKG-INFO
LasBuildSeg.egg-info/SOURCES.txt
LasBuildSeg.egg-info/dependency_links.txt
LasBuildSeg.egg-info/requires.txt
LasBuildSeg.egg-info/top_level.txt
LasBuildSeg/.ipynb_checkpoints/LasBuildSeg-checkpoint.py